examples/__init__.py
examples/basic_example.py
tqdm_multiprocess/__init__.py
tqdm_multiprocess/logger.py
tqdm_multiprocess/std.py
tqdm_multiprocess/tqdm_multiprocess.py
tqdm_multiprocess-0.0.11.dist-info/LICENSE
tqdm_multiprocess-0.0.11.dist-info/METADATA
tqdm_multiprocess-0.0.11.dist-info/WHEEL
tqdm_multiprocess-0.0.11.dist-info/top_level.txt
tqdm_multiprocess-0.0.11.dist-info/RECORD
