Metadata-Version: 2.1
Name: tqdm-multiprocess
Version: 0.0.11
Summary: Easy multiprocessing with tqdm and logging redirected to main process.
Home-page: https://github.com/EleutherAI/tqdm-multiprocess
Author: researcher2
Author-email: 2researcher2@gmail.com
License: UNKNOWN
Platform: UNKNOWN
Classifier: Programming Language :: Python :: 3
Classifier: License :: OSI Approved :: MIT License
Classifier: Operating System :: OS Independent
Requires-Python: >=3.6
Requires-Dist: tqdm
Requires-Dist: colorama
Provides-Extra: dev
Requires-Dist: twine ; extra == 'dev'
